picods/__init__.py
picods/plot/__init__.py
picods/plot/plot.py
picods/table/__init__.py
picods/table/table.py
picods-0.1.6.dist-info/METADATA
picods-0.1.6.dist-info/WHEEL
picods-0.1.6.dist-info/RECORD
