Metadata-Version: 2.1
Name: picods
Version: 0.1.6
Summary: Pico Data Science: A small, personal use case, Data Science library.
License: MIT
Author: Pablo
Author-email: pablohuggem@gmail.com
Requires-Python: >=3.8,<4.0
Classifier: License :: OSI Approved :: MIT License
Classifier: Programming Language :: Python :: 3
Classifier: Programming Language :: Python :: 3.8
Classifier: Programming Language :: Python :: 3.9
Classifier: Programming Language :: Python :: 3.10
Classifier: Programming Language :: Python :: 3.11
Requires-Dist: matplotlib (>=3.7.0,<4.0.0)
Requires-Dist: pandas (>=1.5.3,<2.0.0)
